ytcontroller/__init__.py
ytcontroller-0.0.4.dist-info/LICENCE.txt
ytcontroller-0.0.4.dist-info/METADATA
ytcontroller-0.0.4.dist-info/WHEEL
ytcontroller-0.0.4.dist-info/top_level.txt
ytcontroller-0.0.4.dist-info/RECORD
