Metadata-Version: 2.1
Name: ytcontroller
Version: 0.0.4
Summary: Youtube Controller through hand gestures
Home-page: UNKNOWN
Author: Mihir Panchal
Author-email: mihirpanchal5400@gmail.com
License: MIT
Keywords: yt,youtube,controller,gestures
Platform: UNKNOWN
Classifier: Development Status :: 5 - Production/Stable
Classifier: Intended Audience :: Education
Classifier: Operating System :: Microsoft :: Windows :: Windows 10
Classifier: License :: OSI Approved :: MIT License
Classifier: Programming Language :: Python :: 3
License-File: LICENCE.txt
Requires-Dist: opencv-contrib-python
Requires-Dist: numpy
Requires-Dist: mediapipe
Requires-Dist: pyautogui
Requires-Dist: tensorflow
